pwreg/__init__.py
pwreg-0.0.1.dist-info/LICENSE.txt
pwreg-0.0.1.dist-info/METADATA
pwreg-0.0.1.dist-info/WHEEL
pwreg-0.0.1.dist-info/top_level.txt
pwreg-0.0.1.dist-info/RECORD
