Metadata-Version: 2.1
Name: pwreg
Version: 0.0.1
Summary: basic package
Home-page: https://github.com/pwardion/pwareg
Author: pwardion
Author-email: ilikobaberkay@gmail.com
License-File: LICENSE.txt
